{
  "doc_identity": "15/2012/QH13",
  "amends": [
    {
      "amending_doc_identity": "15/2012/QH13",
      "amending_article": "1",
      "amending_clause": null,
      "amend_type": null,
      "target_doc_identity": null,
      "target_article": null,
      "target_clause": null,
      "target_point": null,
      "original_text": null,
      "new_text": null
    },
    {
      "amending_doc_identity": "15/2012/QH13",
      "amending_article": "Điều 26",
      "amending_clause": null,
      "amend_type": null,
      "target_doc_identity": null,
      "target_article": "26",
      "target_clause": null,
      "target_point": null,
      "original_text": null,
      "new_text": null
    },
    {
      "amending_doc_identity": "15/2012/QH13",
      "amending_article": "Điều 36",
      "amending_clause": null,
      "amend_type": null,
      "target_doc_identity": null,
      "target_article": "36",
      "target_clause": null,
      "target_point": null,
      "original_text": null,
      "new_text": null
    },
    {
      "amending_doc_identity": "15/2012/QH13",
      "amending_article": "Điều 75",
      "amending_clause": null,
      "amend_type": null,
      "target_doc_identity": null,
      "target_article": "75",
      "target_clause": null,
      "target_point": null,
      "original_text": null,
      "new_text": null
    },
    {
      "amending_doc_identity": "15/2012/QH13",
      "amending_article": "Điều 121",
      "amending_clause": null,
      "amend_type": null,
      "target_doc_identity": null,
      "target_article": "121",
      "target_clause": null,
      "target_point": null,
      "original_text": null,
      "new_text": null
    },
    {
      "amending_doc_identity": "15/2012/QH13",
      "amending_article": "Điều 134",
      "amending_clause": null,
      "amend_type": "sửa đổi, bổ sung",
      "target_doc_identity": null,
      "target_article": "134",
      "target_clause": null,
      "target_point": null,
      "original_text": null,
      "new_text": null
    },
    {
      "amending_doc_identity": "15/2012/QH13",
      "amending_article": "Điều 138",
      "amending_clause": null,
      "amend_type": "sửa đổi, bổ sung",
      "target_doc_identity": null,
      "target_article": "138",
      "target_clause": null,
      "target_point": null,
      "original_text": null,
      "new_text": null
    },
    {
      "amending_doc_identity": "15/2012/QH13",
      "amending_article": "Điều 142",
      "amending_clause": null,
      "amend_type": null,
      "target_doc_identity": null,
      "target_article": "142",
      "target_clause": null,
      "target_point": null,
      "original_text": null,
      "new_text": null
    }
  ]
}